event_stream/__init__.py
event_stream/_version.py
event_stream/dao.py
event_stream/event.py
event_stream/event_stream_base.py
event_stream/event_stream_consumer.py
event_stream/event_stream_producer.py
event_stream/util.py
event_stream/models/__init__.py
event_stream/models/model.py
amba_event_stream-1.0.3.dist-info/LICENSE
amba_event_stream-1.0.3.dist-info/METADATA
amba_event_stream-1.0.3.dist-info/WHEEL
amba_event_stream-1.0.3.dist-info/top_level.txt
amba_event_stream-1.0.3.dist-info/RECORD
