Metadata-Version: 2.1
Name: amba-event-stream
Version: 1.0.3
Summary: amba-event-stream for kafka
Home-page: UNKNOWN
Author: Lukas Jesche
Author-email: lukas.jesche.se@gmail.com
License: UNKNOWN
Platform: UNKNOWN
Classifier: Programming Language :: Python :: 3
Classifier: License :: OSI Approved :: MIT License
Classifier: Operating System :: OS Independent
Requires-Python: >=3.6
Requires-Dist: kafka-python
Requires-Dist: sqlalchemy
Requires-Dist: psycopg2
